{
  "id": "lab-19-login-messages",
  "title": "Lab 19: Login Greeting Messages",
  "description": "Configure both a user-specific and a global login greeting with clearer host distribution.",
  "objective_tags": [
    "users-sudo-ssh"
  ],
  "supported_modes": [
    "lab"
  ],
  "time_limit_minutes": 25,
  "tracks": [
    "rhcsa9"
  ],
  "rhel_major": 9,
  "vm_scripts": {
    "client": "scripts/client.sh",
    "server": "scripts/server.sh"
  },
  "flags": {
    "password_recovery": false,
    "requires_server": true
  },
  "content": {
    "lab": {
      "tasks": [
        "On server, configure a login message for user orien19 that says: Welcome to you, user Orien, you are amazing!",
        "Configure a global login message on both client and server so any user receives: Welcome [username], you are logged in! with the actual login name."
      ],
      "hints": [
        "Per-user shell startup content belongs in the user home.",
        "A profile.d script is the cleanest way to apply the same greeting globally."
      ],
      "checks": [
        "test -f /etc/profile.d/lab19-greeting.sh && grep -Fq \"Welcome ${USER}, you are logged in!\" /etc/profile.d/lab19-greeting.sh",
        "# server test -f /etc/profile.d/lab19-greeting.sh && grep -Fq \"Welcome ${USER}, you are logged in!\" /etc/profile.d/lab19-greeting.sh",
        "# server test -f /home/orien19/.bash_profile && grep -Fq \"Welcome to you, user Orien, you are amazing!\" /home/orien19/.bash_profile"
      ],
      "solution_outline": [
        "Create orien19 on server and add the user-specific message.",
        "Deploy the same profile.d greeting script on both hosts."
      ],
      "task_titles": [
        "Create the per-user greeting on server",
        "Create the global login greeting on both systems"
      ],
      "task_points": [
        15,
        15
      ],
      "solution_commands": [
        [
          "id orien19 >/dev/null 2>&1 || useradd -m orien19",
          "echo 'echo \"Welcome to you, user Orien, you are amazing!\"' >> /home/orien19/.bash_profile",
          "chown orien19:orien19 /home/orien19/.bash_profile"
        ],
        [
          "cat > /etc/profile.d/lab19-greeting.sh <<'EOF'",
          "echo \"Welcome ${USER}, you are logged in!\"",
          "EOF",
          "chmod 644 /etc/profile.d/lab19-greeting.sh",
          "# Run on server",
          "cat > /etc/profile.d/lab19-greeting.sh <<'EOF'",
          "echo \"Welcome ${USER}, you are logged in!\"",
          "EOF",
          "chmod 644 /etc/profile.d/lab19-greeting.sh"
        ]
      ]
    }
  }
}
